calender_merger/__init__.py
calender_merger/__main__.py
calender_merger/app.py
calender_merger/static/index.html
calender_merger/templates/meetups-list.html
calender_merger-0.0.4.dist-info/DESCRIPTION.rst
calender_merger-0.0.4.dist-info/METADATA
calender_merger-0.0.4.dist-info/RECORD
calender_merger-0.0.4.dist-info/WHEEL
calender_merger-0.0.4.dist-info/metadata.json
calender_merger-0.0.4.dist-info/top_level.txt
