Metadata-Version: 2.0
Name: calender-merger
Version: 0.0.4
Summary: Python web server for merging calenders.
Home-page: https://github.com/niccokunzmann/calender_merger
Author: Nicco Kunzmann
Author-email: niccokunzmann@rambler.ru
License: LGPL
Keywords: web calender
Platform: UNKNOWN
Classifier: Intended Audience :: Developers
Classifier: License :: OSI Approved :: GNU Lesser General Public License v3 (LGPLv3)
Classifier: Topic :: Software Development :: Libraries :: Python Modules
Classifier: Topic :: Utilities
Classifier: Natural Language :: English
Classifier: Operating System :: OS Independent
Classifier: Programming Language :: Python :: 3 :: Only
Classifier: Development Status :: 5 - Production/Stable
Requires-Dist: bottle (==0.12.9)
Requires-Dist: requests (==2.10.0)
